{
  "$schema": "https://schemas.wp.org/trunk/block.json",
  "apiVersion": 3,
  "name": "cc/testimonial",
  "version": "0.1.0",
  "title": "Best testimonial block ever!",
  "category": "design",
  "icon": "testimonial",
  "description": "testimonial",
  "example": {},
  "supports": {
    "html": false
  },
  "textdomain": "testimonial",
  "editorScript": "file:./index.js",
  "editorStyle": "file:./index.css",
  "style": "file:./style-index.css",
  "viewScript": "file:./view.js",
  "keywords": [
    "wctc",
    "high pulp",
    "cc"
  ],
  "attributes": {
    "quote": {
      "type": "string",
      "source": "html",
      "selector": ".quote"
    },
    "author": {
      "type": "string",
      "source": "html",
      "selector": ".author"
    },
    "stars": {
      "type": "number",
      "default": 5
    },
    "avatarURL": {
      "type": "string",
      "default": "http://place-hold.it/75"
    },
    "backgroundColor": {
      "type": "string"
    },
    "textColor": {
      "type": "string"
    }
  }
}